<?xml version="1.0" encoding="utf-8"?>
<money_transfers version="2.0">
<request_type>get_errors_directory</request_type>
<date>10.06.2008 12:23:56 GMT+3</date>
<error>
	<code>0</code>
	<message>справочник ошибок</message>
</error>
<content>
	<time_stamp>805291904512147</time_stamp>
	<rowdata>
		<row id="0" lang="RU" system_message="Успешное завершение" user_message="Успешное завершение"/>
		<row id="1" lang="RU" system_message="Сессия с таким номером уже существует" user_message="Сессия с таким номером уже существует"/>
		<row id="10" lang="RU" system_message="Неверный формат запроса" user_message="Неверный формат запроса"/>
		<row id="1001" lang="RU" system_message="Неизвестная ошибка" user_message="Операция не может быть выполнена"/>
		<row id="1002" lang="RU" system_message="Ошибка OraManager" user_message="Не удалось подключиться к удаленной базе данных"/>
		<row id="1003" lang="RU" system_message="Внутренняя ошибка Oracle" user_message="Не удалось подключиться к удаленной базе данных"/>
		<row id="1004" lang="RU" system_message="Ошибка при выпольнении процедуры в бд" user_message="Не удалось подключиться к удаленной базе данных"/>
		<row id="1005" lang="RU" system_message="Перевод не найден" user_message="Перевод не найден"/>
		<row id="1006" lang="RU" system_message="Неверный формат входных данных" user_message="Проверьте правильность вводимых параметров"/>
		<row id="1007" lang="RU" system_message="Неправильная подпись" user_message="Документ не подписан"/>
		<row id="1008" lang="RU" system_message="Невозможно создать подпись" user_message="Операция не может быть выполнена"/>
		<row id="1009" lang="RU" system_message="XML-документ сформирован неправильно" user_message="Операция не может быть выполнена"/>
		<row id="1010" lang="RU" system_message="Ошибка gzip" user_message="Операция не может быть выполнена"/>
		<row id="1011" lang="RU" system_message="Короткий открытый ключ" user_message="Длина открытого ключа не должена быть менее 1024 бит"/>
		<row id="1012" lang="RU" system_message="Ошибка операции с файлом" user_message="Операция не может быть выполнена"/>
		<row id="1013" lang="RU" system_message="Неудалось сделать запис в лог-файле" user_message="Операция не может быть выполнена"/>
		<row id="1014" lang="RU" system_message="Вычисленная комиссия и комиссия указаная в запросе не совпадают" user_message="Комиссия указана неправильно"/>
		<row id="1015" lang="RU" system_message="Не удалось определить название системы денежных переводов" user_message="Операция не может быть выполнена"/>
		<row id="1016" lang="RU" system_message="Истек срок действия карты" user_message="Истек срок действия карты клиента"/>
		<row id="1017" lang="RU" system_message="Ошибка Юнистрим" user_message="Юнистрим не может выполнить данную операцию"/>
		<row id="1018" lang="RU" system_message="Ошибка Анелик" user_message="Анелик не может выполнить данную операцию"/>
		<row id="1019" lang="RU" system_message="Ошибка MoneyGram" user_message="MoneyGram не может выполнить данную операцию"/>
		<row id="1020" lang="RU" system_message="Дробная сумма перевода" user_message="Сумма перевода должна быть указана без копеек"/>
		<row id="1021" lang="RU" system_message="Неправильная фамилия" user_message="Фамилия введена неверно"/>
		<row id="1022" lang="RU" system_message="Неправильное имя" user_message="Имя введено неверно"/>
		<row id="1023" lang="RU" system_message="Неправильное отчество" user_message="Отчество введено неверно"/>
		<row id="1024" lang="RU" system_message="Неправильная дата рождения" user_message="Неверно введена дата рождения"/>
		<row id="1025" lang="RU" system_message="Неправильное место рождения" user_message="Место рождения введено неверно"/>
		<row id="1026" lang="RU" system_message="Неправильная страна" user_message="Страна указана неверно"/>
		<row id="1027" lang="RU" system_message="Неправильный номер банка" user_message="Неверно введен номер банка"/>
		<row id="1028" lang="RU" system_message="Неправильный номер телефона" user_message="Неверно введен номер телефона"/>
		<row id="1029" lang="RU" system_message="Неправильный email" user_message="Неверно введен адрес эл. почты"/>
		<row id="103" lang="RU" system_message="Запрещена установка OFF-LINE режима платежей" user_message="Запрещена установка OFF-LINE режима платежей"/>
		<row id="1030" lang="RU" system_message="Неправильный номер мобильного телефона" user_message="Неверно введен номер мобильного телефона"/>
		<row id="1031" lang="RU" system_message="Неправильный резидент" user_message="Неверно введен идентификатор резидента"/>
		<row id="1032" lang="RU" system_message="Неправильный тип" user_message="Неверно введен тип"/>
		<row id="1033" lang="RU" system_message="Неправильный номер серии" user_message="Неверно введен номер серии"/>
		<row id="1034" lang="RU" system_message="Неправильный номер" user_message="Неверно введен номер"/>
		<row id="1035" lang="RU" system_message="Неправильная дата выдачи документа" user_message="Неверно введена дата выдачи документа"/>
		<row id="1036" lang="RU" system_message="Неправильное название организации, выдавшей документ" user_message="Неверно введено название организации, выдавшей документ"/>
		<row id="1037" lang="RU" system_message="Неправильный идентификатор организации, выдавшей документ" user_message="Неверно введен идентификатор организации, выдавшей документ"/>
		<row id="1038" lang="RU" system_message="Неправильный срок действия" user_message="Неверно введен срок действия"/>
		<row id="1039" lang="RU" system_message="Неправильная валюта" user_message="Неверно введен код валюты"/>
		<row id="1040" lang="RU" system_message="Неправильный номер СП" user_message="Неверно введен номер системы денежных переводов"/>
		<row id="1041" lang="RU" system_message="Неправильный номер транзакции" user_message="Неверно введен номер транзакции"/>
		<row id="1042" lang="RU" system_message="Неправильная комиссия" user_message="Неверно введена сумма комиссии"/>
		<row id="1043" lang="RU" system_message="Неправильная комиссия" user_message="Неверно введена сумма комиссии"/>
		<row id="1044" lang="RU" system_message="Неправильная сумма" user_message="Неверно введена сумма"/>
		<row id="1045" lang="RU" system_message="Неправильная итоговая сумма" user_message="Неверно введена итоговая сумма"/>
		<row id="1046" lang="RU" system_message="Необходимо указывать только одну из сумм: amount или amount_total" user_message="Необходимо указывать только одну из сумм: amount или amount_total"/>
		<row id="1047" lang="RU" system_message="Суммы могут присутствовать только в одном из блоков: input_amounts или send_amounts" user_message="Суммы могут присутствовать только в одном из блоков: input_amounts или send_amounts"/>
		<row id="1048" lang="RU" system_message="Неправильный номер банка-получателя" user_message="Неверно введен идентификатор банка, выдающего перевод"/>
		<row id="1049" lang="RU" system_message="Введен неправильный пароль" user_message="Введен неправильный пароль"/>
		<row id="105" lang="RU" system_message="Общая ошибка системы" user_message="Общая ошибка системы"/>
		<row id="1050" lang="RU" system_message="Неправильный пароль" user_message="Неправильный пароль"/>
		<row id="1051" lang="RU" system_message="Неправильный тип поиска" user_message="Тип поиска указан неправильно"/>
		<row id="1052" lang="RU" system_message="Неправильный номер карточки" user_message="Номер карточки указан неправильно"/>
		<row id="1053" lang="RU" system_message="Неправильный владелец карточки" user_message="Владелец карточки указан неправильно"/>
		<row id="1054" lang="RU" system_message="Неизвестный тип запроса" user_message="Операция не может быть выполнена"/>
		<row id="1055" lang="RU" system_message="Неправильный код транзакции" user_message="Неверно введен код транзакции"/>
		<row id="1056" lang="RU" system_message="Неправильная метка времени" user_message="Неверно введена метка обновления справочника"/>
		<row id="1057" lang="RU" system_message="Неправильная дата" user_message="Дата введена неверно"/>
		<row id="1058" lang="RU" system_message="Неправильный номер уведомления" user_message="Номер уведомления введен неверно"/>
		<row id="1059" lang="RU" system_message="Неправильное значение в поле start_date" user_message="Значение start_date указано неверно"/>
		<row id="1060" lang="RU" system_message="Неправильное значение в поле end_date" user_message="Неправильное значение в поле end_date"/>
		<row id="11" lang="RU" system_message="Сессиия с таким номером не существует" user_message="Сессиия с таким номером не существует"/>
		<row id="110" lang="RU" system_message="Не заполнено обязательное поле или его значение недопустимо" user_message="Не все обязательные данные введены. Пожалуйста, проверьте."/>
		<row id="112" lang="RU" system_message="Передана неверная дата" user_message="Передана неверная дата"/>
		<row id="12" lang="RU" system_message="Запрос сделан с незарегистрированного IP" user_message="Запрос сделан с незарегистрированного IP"/>
		<row id="120" lang="RU" system_message="Ошибка добавления заявки на отмену платежа в базу данных" user_message="Ошибка добавления заявки на отмену платежа в базу данных"/>
		<row id="121" lang="RU" system_message="Не удалось изменить статус заявки" user_message="Не удалось изменить статус заявки"/>
		<row id="122" lang="RU" system_message="Корректировка платежа уже зарегистрирована" user_message="Корректировка платежа уже зарегистрирована"/>
		<row id="123" lang="RU" system_message="Отмена платежа уже зарегистрирована" user_message="Отмена платежа уже зарегистрирована"/>
		<row id="125" lang="RU" system_message="Заявка не найдена" user_message="Заявка не найдена"/>
		<row id="130" lang="RU" system_message="Документы (проводки) уже сторнированы" user_message="Документы (проводки) уже сторнированы"/>
		<row id="131" lang="RU" system_message="Документ с такими данными уже существует" user_message="Документ с такими данными уже существует"/>
		<row id="132" lang="RU" system_message="Документы(проводки) с такими данными не найдены" user_message="Документы(проводки) с такими данными не найдены"/>
		<row id="133" lang="RU" system_message="Общая ошибка системы" user_message="Общая ошибка системы"/>
		<row id="134" lang="RU" system_message="Не найден ключ по указанному коду" user_message="Не найден ключ по указанному коду"/>
		<row id="15" lang="RU" system_message="Платежи данному оператору не поддерживаются системой" user_message="Платежи данному оператору не поддерживаются системой"/>
		<row id="151" lang="RU" system_message="Мегафон - отмена платежа за текущий день" user_message="Мегафон - отмена платежа за текущий день"/>
		<row id="152" lang="RU" system_message="Мегафон - отмена платежа: срок более месяца" user_message="Мегафон - отмена платежа: срок более месяца"/>
		<row id="162" lang="RU" system_message="МТС - отмена платежа: срок более месяца" user_message="МТС - отмена платежа: срок более месяца"/>
		<row id="163" lang="RU" system_message="МТС - отмена платежа: сумма платежа меньше допустимой" user_message="МТС - отмена платежа: сумма платежа меньше допустимой"/>
		<row id="17" lang="RU" system_message="Номер телефона не соответствует введенному ранее" user_message="Номер телефона не соответствует введенному ранее"/>
		<row id="18" lang="RU" system_message="Сумма платежа не соответствует введенной ранее" user_message="Сумма платежа не соответствует введенной ранее"/>
		<row id="19" lang="RU" system_message="Номер счета(контракта) не соответствует введенному ранее" user_message="Номер счета(контракта) не соответствует введенному ранее"/>
		<row id="2" lang="RU" system_message="Неверный код дилера" user_message="Неверный код дилера"/>
		<row id="20" lang="RU" system_message="Платеж находится в состоянии завершения" user_message="Платеж находится в состоянии завершения"/>
		<row id="21" lang="RU" system_message="Недостаточно средств для проведения платежа" user_message="Недостаточно средств для проведения платежа"/>
		<row id="22" lang="RU" system_message="Платеж не принят. Ошибка при переводе средств" user_message="Платеж не принят. Ошибка при переводе средств"/>
		<row id="23" lang="RU" system_message="Неверный номер телефона/счета" user_message="Неверный номер телефона/счета"/>
		<row id="24" lang="RU" system_message="Ошибка связи с сервером провайдера" user_message="Ошибка связи с сервером провайдера"/>
		<row id="25" lang="RU" system_message="Работа шлюза преостановлена" user_message="Работа шлюза преостановлена"/>
		<row id="26" lang="RU" system_message="Работа дилера преостановлена" user_message="Работа дилера преостановлена"/>
		<row id="27" lang="RU" system_message="Операции по счету приостановлены" user_message="Операции по счету приостановлены"/>
		<row id="3" lang="RU" system_message="Неверный код точки приема" user_message="Неверный код точки приема"/>
		<row id="30" lang="RU" system_message="Общая ошибка системы" user_message="Общая ошибка системы"/>
		<row id="32" lang="RU" system_message="Платеж с этими данными уже был принят к обработке за последний час" user_message="Платеж с этими данными уже был принят к обработке за последний час"/>
		<row id="33" lang="RU" system_message="Карты указанного номинала на данный момент в системе отсутствуют" user_message="Карты указанного номинала на данный момент в системе отсутствуют"/>
		<row id="333" lang="RU" system_message="Неизвестная ошибка" user_message="Неизвестная ошибка"/>
		<row id="34" lang="RU" system_message="Платеж с таким номером не найден" user_message="Платеж с таким номером не найден"/>
		<row id="35" lang="RU" system_message="Ошибка при изменении состояния платежа" user_message="Ошибка при изменении состояния платежа"/>
		<row id="36" lang="RU" system_message="Неверный статус платежа" user_message="Неверный статус платежа"/>
		<row id="37" lang="RU" system_message="Попытка обращения в шлюз, отличный от шлюза на предыдущем шаге" user_message="Попытка обращения в шлюз, отличный от шлюза на предыдущем шаге"/>
		<row id="38" lang="RU" system_message="Неверная дата. Возможно срок действия платежа истек" user_message="Неверная дата. Возможно срок действия платежа истек"/>
		<row id="39" lang="RU" system_message="Неверный счет" user_message="Неверный счет"/>
		<row id="4" lang="RU" system_message="Неверный код оператора. Обратитесь к администратору." user_message="Неверный код оператора. Обратитесь к администратору."/>
		<row id="40" lang="RU" system_message="Карта указанного номинала в системе не зарегистрирована" user_message="Карта указанного номинала в системе не зарегистрирована"/>
		<row id="41" lang="RU" system_message="Ошибка добавления данных платежа в базу данных" user_message="Ошибка добавления данных платежа в базу данных"/>
		<row id="42" lang="RU" system_message="Ошибка при сохранении чека в базе данных" user_message="Ошибка при сохранении чека в базе данных"/>
		<row id="43" lang="RU" system_message="Сеанс Вашей работы в системе недействителен (возможно, истек срок действия сессии), попробуйте войти заново" user_message="Сеанс Вашей работы в системе недействителен (возможно, истек срок действия сессии), попробуйте войти заново"/>
		<row id="44" lang="RU" system_message="Клиент не может работать на этом Торг.Сервере" user_message="Клиент не может работать на этом Торг.Сервере"/>
		<row id="45" lang="RU" system_message="Отсутствуют права доступа в данный раздел. Обратитесь к администратору." user_message="Операция не может быть выполнена. Обратитесь в службу поддержки."/>
		<row id="46" lang="RU" system_message="Не удалось завершить ошибочный платеж" user_message="Не удалось завершить ошибочный платеж"/>
		<row id="47" lang="RU" system_message="Сработало временнОе ограничение прав" user_message="Сработало временнОе ограничение прав"/>
		<row id="48" lang="RU" system_message="Ошибка при сохранении данных сессии в базе данных" user_message="Ошибка при сохранении данных сессии в базе данных"/>
		<row id="5" lang="RU" system_message="Неверный формат кода сессии" user_message="Неверный формат кода сессии"/>
		<row id="50" lang="RU" system_message="Проведение платежей в системе временно невозможно" user_message="Проведение платежей в системе временно невозможно"/>
		<row id="51" lang="RU" system_message="Не найдены данные в базе. Обратитесь в службу поддержки." user_message="Операция не может быть выполнена. Обратитесь в службу поддержки."/>
		<row id="52" lang="RU" system_message="Возможно дилер заблокирован" user_message="Возможно дилер заблокирован"/>
		<row id="53" lang="RU" system_message="Возможно точки приема заблокирована" user_message="Возможно точки приема заблокирована"/>
		<row id="54" lang="RU" system_message="Возможно оператор заблокирован" user_message="Возможно оператор заблокирован"/>
		<row id="55" lang="RU" system_message="Ожидался дилер другого типа" user_message="Ожидался дилер другого типа"/>
		<row id="56" lang="RU" system_message="Ожидалась точка другого типа" user_message="Ожидалась точка другого типа"/>
		<row id="57" lang="RU" system_message="Ожидался оператор другого типа" user_message="Ожидался оператор другого типа"/>
		<row id="6" lang="RU" system_message="Неверная ЭЦП" user_message="Неверная ЭЦП"/>
		<row id="7" lang="RU" system_message="Неверный формат или значение суммы вне допустимого диапазона" user_message="Неверный формат или значение суммы вне допустимого диапазона"/>
		<row id="701" lang="RU" system_message="Неправильный номер системы ДП" user_message="Неправильный номер системы ДП"/>
		<row id="702" lang="RU" system_message="Неправильный гео-объект" user_message="Неправильный гео-объект"/>
		<row id="703" lang="RU" system_message="Неправильный номер страны" user_message="Неправильный номер страны"/>
		<row id="704" lang="RU" system_message="Неправильный код гео-объекта" user_message="Неправильный код гео-объекта"/>
		<row id="705" lang="RU" system_message="Неправильное название гео-объекта" user_message="Неправильное название гео-объекта"/>
		<row id="706" lang="RU" system_message="Такой гео-объект в уже есть" user_message="Такой гео-объект в уже есть"/>
		<row id="707" lang="RU" system_message="Новый пароль должен отличаться от старого" user_message="Новый пароль должен отличаться от старого"/>
		<row id="708" lang="RU" system_message="Неправильная привязка узла" user_message="Неправильная привязка узла"/>
		<row id="709" lang="RU" system_message="Нельзя переносить узел в другую систему ДП" user_message="Нельзя переносить узел в другую систему ДП"/>
		<row id="71" lang="RU" system_message="Не указана дата завершения действия карты для данного номинала" user_message="Не указана дата завершения действия карты для данного номинала"/>
		<row id="710" lang="RU" system_message="Недопустимая циклическая ссылка" user_message="Недопустимая циклическая ссылка"/>
		<row id="711" lang="RU" system_message="Неправильный номер клиента" user_message="Неправильный номер клиента"/>
		<row id="712" lang="RU" system_message="Нет данных о клиенте" user_message="Нет данных о клиенте"/>
		<row id="713" lang="RU" system_message="Нет паспортных данных о клиенте" user_message="Нет паспортных данных о клиенте"/>
		<row id="714" lang="RU" system_message="Клиент в чёрном списке" user_message="Клиент в чёрном списке"/>
		<row id="715" lang="RU" system_message="Неправильная фамилия" user_message="Неправильная фамилия"/>
		<row id="716" lang="RU" system_message="Неправильное имя" user_message="Неправильное имя"/>
		<row id="717" lang="RU" system_message="Неправильное отчество" user_message="Неправильное отчество"/>
		<row id="718" lang="RU" system_message="Неправильная дата рождения" user_message="Неправильная дата рождения"/>
		<row id="719" lang="RU" system_message="Неправильное место рождения" user_message="Неправильное место рождения"/>
		<row id="72" lang="RU" system_message="Номер карты и ПИН-код должны быть уникальными в рамках одного провайдера" user_message="Номер карты и ПИН-код должны быть уникальными в рамках одного провайдера"/>
		<row id="720" lang="RU" system_message="Неправильная серия документа" user_message="Неправильная серия документа"/>
		<row id="721" lang="RU" system_message="Неправильный номер документа" user_message="Неправильный номер документа"/>
		<row id="722" lang="RU" system_message="Неправильная дата документа" user_message="Неправильная дата документа"/>
		<row id="723" lang="RU" system_message="Неправильное название органа, выпустившего документ" user_message="Неправильное название органа, выпустившего документ"/>
		<row id="724" lang="RU" system_message="Такого клиента нет" user_message="Такого клиента нет"/>
		<row id="725" lang="RU" system_message="Неправильный номер банковской карты или пароль." user_message="Неправильный номер банковской карты или пароль."/>
		<row id="726" lang="RU" system_message="Неправильный пароль ПК" user_message="Неправильный пароль ПК"/>
		<row id="727" lang="RU" system_message="Неправильная дата окончания действия карты" user_message="Неправильная дата окончания действия карты"/>
		<row id="728" lang="RU" system_message="ПК просрочена" user_message="ПК просрочена"/>
		<row id="729" lang="RU" system_message="Неправильный владелец карты" user_message="Неправильный владелец карты"/>
		<row id="730" lang="RU" system_message="Неправильный старый пароль ПК" user_message="Неправильный старый пароль ПК"/>
		<row id="731" lang="RU" system_message="Неправильный новый пароль ПК" user_message="Неправильный новый пароль ПК"/>
		<row id="732" lang="RU" system_message="Пароль слишком короткий" user_message="Пароль слишком короткий"/>
		<row id="733" lang="RU" system_message="Клиент не найден" user_message="Клиент не найден"/>
		<row id="734" lang="RU" system_message="Неправильный тип клиента" user_message="Неправильный тип клиента"/>
		<row id="735" lang="RU" system_message="Система ДП блокирована" user_message="Система ДП блокирована"/>
		<row id="736" lang="RU" system_message="Неправильная валюта" user_message="Неправильная валюта"/>
		<row id="737" lang="RU" system_message="Неправильный номер загрузки" user_message="Неправильный номер загрузки"/>
		<row id="738" lang="RU" system_message="Неправильный банк" user_message="Неправильный банк"/>
		<row id="739" lang="RU" system_message="Неправильная дата правила" user_message="Неправильная дата правила"/>
		<row id="740" lang="RU" system_message="Правило не найдено" user_message="Правило не найдено"/>
		<row id="741" lang="RU" system_message="Такое правило уже есть" user_message="Такое правило уже есть"/>
		<row id="742" lang="RU" system_message="Неправильная дата начала действия правила" user_message="Неправильная дата начала действия правила"/>
		<row id="743" lang="RU" system_message="Неправильный процент вознаграждения" user_message="Неправильный процент вознаграждения"/>
		<row id="744" lang="RU" system_message="Неправильная сумма процентов вознаграждения" user_message="Неправильная сумма процентов вознаграждения"/>
		<row id="745" lang="RU" system_message="Неправильное значение для флага оффлайновой проводки" user_message="Неправильное значение для флага оффлайновой проводки"/>
		<row id="746" lang="RU" system_message="Неправильный номер правила" user_message="Неправильный номер правила"/>
		<row id="747" lang="RU" system_message="Правило изменять нельзя" user_message="Правило изменять нельзя"/>
		<row id="748" lang="RU" system_message="Неправильный тариф" user_message="Неправильный тариф"/>
		<row id="749" lang="RU" system_message="Тариф изменять нельзя" user_message="Тариф изменять нельзя"/>
		<row id="750" lang="RU" system_message="Неправильная тарифная сетка" user_message="Неправильная тарифная сетка"/>
		<row id="751" lang="RU" system_message="Такой тариф уже есть" user_message="Такой тариф уже есть"/>
		<row id="752" lang="RU" system_message="НЕПРАВИЛЬНЫЙ ПАРАМЕТР ДЛЯ ВЫЧИСЛЕНИЯ ТАРИФА" user_message="НЕПРАВИЛЬНЫЙ ПАРАМЕТР ДЛЯ ВЫЧИСЛЕНИЯ ТАРИФА"/>
		<row id="753" lang="RU" system_message="НЕПРАВИЛЬНЫЙ ТИП ГЕОГРАФИЧЕСКОГО ОБЪЕКТА" user_message="НЕПРАВИЛЬНЫЙ ТИП ГЕОГРАФИЧЕСКОГО ОБЪЕКТА"/>
		<row id="754" lang="RU" system_message="Неправильная дата начала действия тарифа" user_message="Неправильная дата начала действия тарифа"/>
		<row id="755" lang="RU" system_message="Неправильный номер тарифа" user_message="Неправильный номер тарифа"/>
		<row id="756" lang="RU" system_message="Такой диапазон тарифной сетки уже есть" user_message="Такой диапазон тарифной сетки уже есть"/>
		<row id="757" lang="RU" system_message="Начальная сумма тарифной сетки не должна быть меньше 1" user_message="Начальная сумма тарифной сетки не должна быть меньше 1"/>
		<row id="758" lang="RU" system_message="Неправильная величина тарифа" user_message="Неправильная величина тарифа"/>
		<row id="759" lang="RU" system_message="Неправильный номер тарифной сетки" user_message="Неправильный номер тарифной сетки"/>
		<row id="760" lang="RU" system_message="Неправильный тип документа" user_message="Неправильный тип документа"/>
		<row id="761" lang="RU" system_message="Неправильный тип ПК" user_message="Неправильный тип ПК"/>
		<row id="762" lang="RU" system_message="Не найдена система ДП" user_message="Не найдена система ДП"/>
		<row id="763" lang="RU" system_message="Оператор не относится к заданному отделению банка" user_message="Оператор не относится к заданному отделению банка"/>
		<row id="764" lang="RU" system_message="Не указано значение платы за перевод" user_message="Не указано значение платы за перевод"/>
		<row id="765" lang="RU" system_message="Не указан код перевода" user_message="Не указан код перевода"/>
		<row id="766" lang="RU" system_message="Не найден перевод" user_message="Не найден перевод"/>
		<row id="767" lang="RU" system_message="Неверная комиссия" user_message="Указанная комиссия не совпадает с базовой"/>
		<row id="768" lang="RU" system_message="Неправильная сумма перевода" user_message="Неправильная сумма перевода"/>
		<row id="769" lang="RU" system_message="Не указан номер перевода" user_message="Не указан номер перевода"/>
		<row id="770" lang="RU" system_message="Дилер не имеет счета в валюте перевода" user_message="Дилер не имеет счета в валюте перевода"/>
		<row id="771" lang="RU" system_message="Такой доступ уже есть" user_message="Такой доступ уже есть"/>
		<row id="772" lang="RU" system_message="Неправильный тип тарифа" user_message="Неправильный тип тарифа"/>
		<row id="773" lang="RU" system_message="Неправильный тип записи в сетке" user_message="Неправильный тип записи в сетке"/>
		<row id="774" lang="RU" system_message="Неправильный параметр для сетк" user_message="Неправильный параметр для сетк"/>
		<row id="775" lang="RU" system_message="Нет связи с внешней базой данных" user_message="Нет связи с внешней базой данных"/>
		<row id="777" lang="RU" system_message="Перевод с такими параметрами уже создан в системе" user_message="Перевод с такими параметрами уже создан в системе"/>
		<row id="778" lang="RU" system_message="Перевод уже запрошен на изменение" user_message="Перевод уже запрошен на изменение"/>
		<row id="779" lang="RU" system_message="Перевод уже запрошен на возврат" user_message="Перевод уже запрошен на возврат"/>
		<row id="780" lang="RU" system_message="ПЕРЕВОД УЖЕ ВОЗВРАЩЕН" user_message="ПЕРЕВОД УЖЕ ВОЗВРАЩЕН"/>
		<row id="781" lang="RU" system_message="Перевод уже выдан" user_message="Перевод уже выдан"/>
		<row id="783" lang="RU" system_message="ПЕРЕВОД НЕ ЗАПРОШЕН НА ИЗМЕНЕНИЕ" user_message="ПЕРЕВОД НЕ ЗАПРОШЕН НА ИЗМЕНЕНИЕ"/>
		<row id="784" lang="RU" system_message="ПЕРЕВОД НЕ ЗАПРОШЕН НА ВОЗВРАТ" user_message="ПЕРЕВОД НЕ ЗАПРОШЕН НА ВОЗВРАТ"/>
		<row id="785" lang="RU" system_message="НЕВЕРНЫЙ ТИП СООБЩЕНИЯ" user_message="НЕВЕРНЫЙ ТИП СООБЩЕНИЯ"/>
		<row id="788" lang="RU" system_message="НЕ НАЙДЕН ТИП КОДА (ДОПОПИСАНИЕ) УЧАСТНИКА С КОНСТАНТОЙ" user_message="НЕ НАЙДЕН ТИП КОДА (ДОПОПИСАНИЕ) УЧАСТНИКА С КОНСТАНТОЙ"/>
		<row id="789" lang="RU" system_message="ДЛЯ ОТПРАВИТЕЛЯ СООБЩЕНИЯ НЕ УКАЗАН ИНТЕФЕЙС ОБМЕНА В СПРАВОЧНИКЕ ПАРТНЕРОВ АНЕЛИК" user_message="ДЛЯ ОТПРАВИТЕЛЯ СООБЩЕНИЯ НЕ УКАЗАН ИНТЕФЕЙС ОБМЕНА В СПРАВОЧНИКЕ ПАРТНЕРОВ АНЕЛИК"/>
		<row id="790" lang="RU" system_message="ОТПРАВИТЕЛЬ СООБЩЕНИЯ ИСПОЛЬЗУЕТ НЕДОПУСТИМУЮ ТРАНСПОРТНУЮ СИСТЕМУ ВМЕСТО РАЗРЕШЕННОЙ " user_message="ОТПРАВИТЕЛЬ СООБЩЕНИЯ ИСПОЛЬЗУЕТ НЕДОПУСТИМУЮ ТРАНСПОРТНУЮ СИСТЕМУ ВМЕСТО РАЗРЕШЕННОЙ "/>
		<row id="791" lang="RU" system_message="ТЕКУЩЕМУ УЧАСТНИКУ НЕ РАЗРЕШЕНО ЗАГРУЖАТЬ СООБЩЕНИЯ ИЗ НАПРАВЛЕНИЯ " user_message="ТЕКУЩЕМУ УЧАСТНИКУ НЕ РАЗРЕШЕНО ЗАГРУЖАТЬ СООБЩЕНИЯ ИЗ НАПРАВЛЕНИЯ "/>
		<row id="792" lang="RU" system_message="КОД ПОДТВЕРЖДЕНИЯ НЕ ПОДДЕРЖИВАЕТСЯ" user_message="КОД ПОДТВЕРЖДЕНИЯ НЕ ПОДДЕРЖИВАЕТСЯ"/>
		<row id="793" lang="RU" system_message="НЕ НАЙДЕНО СООБЩЕНИЕ ДЛЯ ПОДТВЕРЖДЕНИЯ/НАЙДЕНО БОЛЕЕ ОДНОГО СООБЩЕНИЯ ДЛЯ ПОДТВЕРЖДЕНИЯ" user_message="НЕ НАЙДЕНО СООБЩЕНИЕ ДЛЯ ПОДТВЕРЖДЕНИЯ/НАЙДЕНО БОЛЕЕ ОДНОГО СООБЩЕНИЯ ДЛЯ ПОДТВЕРЖДЕНИЯ"/>
		<row id="794" lang="RU" system_message="Не найден пункт отправки /отправка платежей в валюте запрещена для пункта отправки" user_message="Не найден пункт отправки /отправка платежей в валюте запрещена для пункта отправки"/>
		<row id="795" lang="RU" system_message="Нельзя отправить данный перевод в указанный пункт выдачи. Выберите другой пункт или валюту." user_message="Нельзя отправить данный перевод в указанный пункт выдачи. Выберите другой пункт или валюту."/>
		<row id="797" lang="RU" system_message="НЕВЕРНО УКАЗАНА ВАЛЮТА ВЫДАЧИ ДЕНЕГ " user_message="НЕВЕРНО УКАЗАНА ВАЛЮТА ВЫДАЧИ ДЕНЕГ "/>
		<row id="798" lang="RU" system_message="СУММА ПЕРЕВОДА ВЫХОДИТ ЗА ДОПУСТИМЫЕ ГРАНИЦЫ  ДЛЯ ПУНКТА ОТПРАВКИ " user_message="СУММА ПЕРЕВОДА ВЫХОДИТ ЗА ДОПУСТИМЫЕ ГРАНИЦЫ  ДЛЯ ПУНКТА ОТПРАВКИ "/>
		<row id="799" lang="RU" system_message="СУММА ПЕРЕВОДА ВЫХОДИТ ЗА ДОПУСТИМЫЕ ГРАНИЦЫ  ДЛЯ ПУНКТА ВЫДАЧИ " user_message="СУММА ПЕРЕВОДА ВЫХОДИТ ЗА ДОПУСТИМЫЕ ГРАНИЦЫ  ДЛЯ ПУНКТА ВЫДАЧИ "/>
		<row id="8" lang="RU" system_message="Неверный формат номера телефона" user_message="Неверный формат номера телефона"/>
		<row id="802" lang="RU" system_message="УКАЗАННАЯ МАТРИЦА КУРСОВ НЕ НАЙДЕНА" user_message="УКАЗАННАЯ МАТРИЦА КУРСОВ НЕ НАЙДЕНА"/>
		<row id="803" lang="RU" system_message="У ПУНКТА ВЫДАЧИ  НЕ УКАЗАНО НАПРАВЛЕНИЕ В СПРАВОЧНИКЕ УЧАСТНИКОВ" user_message="У ПУНКТА ВЫДАЧИ  НЕ УКАЗАНО НАПРАВЛЕНИЕ В СПРАВОЧНИКЕ УЧАСТНИКОВ"/>
		<row id="804" lang="RU" system_message="ТЕКУЩЕМУ УЧАСТНИКУ  НЕ РАЗРЕШЕНО СОВЕРШАТЬ ОПЕРАЦИИ ОТ ИМЕНИ ПУНКТА ОТПРАВКИ , ТАК КАК ТЕКУЩИЙ УЧАСТНИК НЕ ЯВЛЯЕТСЯ ОДНИМ ИЗ РОДИТЕЛЕЙ ПУНКТА ОТПРАВКИ В ДЕРЕВЕ УЧАСТНИКОВ" user_message="ТЕКУЩЕМУ УЧАСТНИКУ  НЕ РАЗРЕШЕНО СОВЕРШАТЬ ОПЕРАЦИИ ОТ ИМЕНИ ПУНКТА ОТПРАВКИ , ТАК КАК ТЕКУЩИЙ УЧАСТНИК НЕ ЯВЛЯЕТСЯ ОДНИМ ИЗ РОДИТЕЛЕЙ ПУНКТА ОТПРАВКИ В ДЕРЕВЕ УЧАСТНИКОВ"/>
		<row id="805" lang="RU" system_message="НАПРАВЛЕНИЕ , ОТ КОТОРОГО ДОЛЖНО ПРИХОДИТЬ СООБЩЕНИЕ, НЕ СООТВЕТСТВУЕТ OFF-LINE НАПРАВЛЕНИЮ , ОТ КОТОРОГО ПОЛУЧЕНО СООБЩЕНИЕ" user_message="НАПРАВЛЕНИЕ , ОТ КОТОРОГО ДОЛЖНО ПРИХОДИТЬ СООБЩЕНИЕ, НЕ СООТВЕТСТВУЕТ OFF-LINE НАПРАВЛЕНИЮ , ОТ КОТОРОГО ПОЛУЧЕНО СООБЩЕНИЕ"/>
		<row id="806" lang="RU" system_message="КОМИССИЯ МЕНЬШЕ НУЛЯ" user_message="КОМИССИЯ МЕНЬШЕ НУЛЯ"/>
		<row id="807" lang="RU" system_message="ВХОДЯЩАЯ КОМИССИЯ В СИСТЕМУ НЕ СООТВЕТСТВУЕТ РАСЧЕТНОЙ" user_message="ВХОДЯЩАЯ КОМИССИЯ В СИСТЕМУ НЕ СООТВЕТСТВУЕТ РАСЧЕТНОЙ"/>
		<row id="810" lang="RU" system_message="Найдено похожее необработанное заявление" user_message="Найдено похожее необработанное заявление"/>
		<row id="811" lang="RU" system_message="Не найдено зявление в  базе" user_message="Не найдено зявление в  базе"/>
		<row id="812" lang="RU" system_message="Клиент не может отправлять рубли" user_message="Клиент не может отправлять рубли"/>
		<row id="813" lang="RU" system_message="Клиенту необходимо сменить системный пароль на пользовательский" user_message="Клиенту необходимо сменить системный пароль на пользовательский"/>
		<row id="814" lang="RU" system_message="Сумма перевода превышает разрешенную для резидента" user_message="Сумма перевода превышает разрешенную для резидента"/>
		<row id="815" lang="RU" system_message="Введенные пароли не совпадают" user_message="Введенные пароли не совпадают"/>
		<row id="9" lang="RU" system_message="Неверный формат номера лицевого счета" user_message="Неверный формат номера лицевого счета"/>
		<row id="901" lang="RU" system_message="Дилер - владелец ваучера должен работать по схеме процессинг" user_message="Дилер - владелец ваучера должен работать по схеме процессинг"/>
		<row id="902" lang="RU" system_message="Некорректный формат даты активации" user_message="Некорректный формат даты активации"/>
		<row id="903" lang="RU" system_message="Запрещена загрузка ваучеров с датой активации в текущем дне" user_message="Запрещена загрузка ваучеров с датой активации в текущем дне"/>
		<row id="904" lang="RU" system_message="Проверьте период пролонгации указанного номинала" user_message="Проверьте период пролонгации указанного номинала"/>
		<row id="905" lang="RU" system_message="Некорректный формат периода пролонгации" user_message="Некорректный формат периода пролонгации"/>
		<row id="906" lang="RU" system_message="Некорректный формат номера карты" user_message="Некорректный формат номера карты"/>
		<row id="907" lang="RU" system_message="Некорректная длина номера карты указанного номинала" user_message="Некорректная длина номера карты указанного номинала"/>
		<row id="908" lang="RU" system_message="Некорректный формат пин-кода" user_message="Некорректный формат пин-кода"/>
		<row id="909" lang="RU" system_message="Некорректная длина пин-кода указанного номинала" user_message="Некорректная длина пин-кода указанного номинала"/>
		<row id="910" lang="RU" system_message="Повторный запрос данных ваучера дилеру не разрешен" user_message="Повторный запрос данных ваучера дилеру не разрешен"/>
		<row id="911" lang="RU" system_message="Число запросов по карте превысило максимальное допустимое" user_message="Число запросов по карте превысило максимальное допустимое"/>
	</rowdata>
</content>
</money_transfers>
